{
  "last_updated": "2026-05-07T21:30:44.875200+00:00",
  "vehicles": [
    {
      "vin": "3C6UR5FJ6NG305274",
      "year": "2022",
      "make": "Ram",
      "model": "2500",
      "nickname": null,
      "odometer_mi": 144383.0,
      "range_mi": 370.3,
      "fuel_pct": 92,
      "fuel_low": false,
      "battery_v": 13.6,
      "tires_psi": {
        "front_left": 69.0,
        "front_right": 69.0,
        "rear_left": 68.0,
        "rear_right": 68.0
      },
      "tires_warning": {
        "front_left": false,
        "front_right": false,
        "rear_left": false,
        "rear_right": false
      },
      "location": {
        "lat": 30.396814,
        "lng": -95.55507,
        "ts": "2026-05-06 22:45:26.808000+00:00",
        "place": "Montgomery County, TX"
      },
      "oil": {
        "interval_mi": 5000,
        "baseline_mi": 143061,
        "miles_since": 1322,
        "miles_to_next": 3678,
        "baseline_set_at": "2026-04-29T19:15:16.496275+00:00",
        "auto_anchored": true
      }
    }
  ]
}